landscapes/constrained.py
landscapes/multi_objective.py
landscapes/single_objective.py
landscapes/utils.py
landscapes-0.0.13.dist-info/licenses/LICENSE.txt
landscapes-0.0.13.dist-info/METADATA
landscapes-0.0.13.dist-info/WHEEL
landscapes-0.0.13.dist-info/top_level.txt
landscapes-0.0.13.dist-info/RECORD
