Metadata-Version: 2.4
Name: landscapes
Version: 0.0.13
Summary: A Python library of standardized optimization test functions
Home-page: https://github.com/nathanrooy/landscapes
Author: Nathan A. Rooy
Author-email: nathanrooy@gmail.com
Classifier: Programming Language :: Python :: 3
Classifier: License :: OSI Approved :: MIT License
Classifier: Operating System :: OS Independent
Requires-Python: >=3.5
License-File: LICENSE.txt
Dynamic: author
Dynamic: author-email
Dynamic: classifier
Dynamic: description
Dynamic: description-content-type
Dynamic: home-page
Dynamic: license-file
Dynamic: requires-python
Dynamic: summary
